rosrepo/__init__.py
rosrepo/__main__.py
rosrepo/cache.py
rosrepo/cmd_bash.py
rosrepo/cmd_build.py
rosrepo/cmd_clean.py
rosrepo/cmd_config.py
rosrepo/cmd_depend.py
rosrepo/cmd_export.py
rosrepo/cmd_find.py
rosrepo/cmd_git.py
rosrepo/cmd_include_exclude.py
rosrepo/cmd_init.py
rosrepo/cmd_list.py
rosrepo/cmd_test.py
rosrepo/common.py
rosrepo/config.py
rosrepo/dummy_pkg_resources.py
rosrepo/git.py
rosrepo/gitlab.py
rosrepo/main.py
rosrepo/resolver.py
rosrepo/terminal_color.py
rosrepo/ui.py
rosrepo/util.py
rosrepo/workspace.py
rosrepo-3.0.90.data/data/share/bash-completion/completions/rosrepo
rosrepo-3.0.90.dist-info/DESCRIPTION.rst
rosrepo-3.0.90.dist-info/METADATA
rosrepo-3.0.90.dist-info/RECORD
rosrepo-3.0.90.dist-info/WHEEL
rosrepo-3.0.90.dist-info/entry_points.txt
rosrepo-3.0.90.dist-info/metadata.json
rosrepo-3.0.90.dist-info/top_level.txt
