Metadata-Version: 2.0
Name: rosrepo
Version: 3.0.90
Summary: Manage ROS workspaces with multiple Gitlab repositories
Home-page: UNKNOWN
Author: Timo Röhling
Author-email: timo.roehling@fkie.fraunhofer.de
License: Apache Software License
Keywords: catkin,ROS,Git
Platform: UNKNOWN
Classifier: Development Status :: 5 - Production/Stable
Classifier: Intended Audience :: Developers
Classifier: Topic :: Software Development :: Build Tools
Classifier: Topic :: Software Development :: Version Control
Classifier: Programming Language :: Python
Requires-Dist: catkin-pkg
Requires-Dist: catkin-tools
Requires-Dist: pygit2
Requires-Dist: python-dateutil
Requires-Dist: pyyaml
Requires-Dist: requests
Requires-Dist: rosdep
Requires-Dist: futures; python_version < "3"
Requires-Dist: scandir; python_version < "3.5"
